{"elements": [{"type": "freeform", "fill": {"type": "solid", "color": "#FFFF66"}, "stroke": "black", "strokeWidth": [0.09525], "points": [{"x": 18, "y": 228, "directive": "moveTo"}, {"x": 0, "y": 245, "directive": "lineTo"}, {"x": 0, "y": 924, "directive": "lineTo"}, {"x": 17, "y": 958, "directive": "lineTo"}, {"x": 138, "y": 958, "directive": "lineTo"}, {"x": 138, "y": 0, "directive": "lineTo"}, {"x": 18, "y": 0, "directive": "lineTo"}, {"x": 0, "y": 21, "directive": "lineTo"}, {"x": 0, "y": 139, "directive": "lineTo"}, {"x": 18, "y": 162, "directive": "lineTo"}, {"x": 18, "y": 228, "directive": "lineTo"}, {"directive": "close"}]}, {"type": "freeform", "fill": {"type": "solid", "color": "red"}, "stroke": "black", "strokeWidth": [0.09525], "points": [{"x": 2, "y": 924, "directive": "moveTo"}, {"x": 140, "y": 924, "directive": "lineTo"}]}, {"type": "freeform", "fill": {"type": "solid", "color": "red"}, "stroke": "black", "strokeWidth": [0.09525], "points": [{"x": 1, "y": 244, "directive": "moveTo"}, {"x": 138, "y": 244, "directive": "lineTo"}]}, {"type": "freeform", "fill": {"type": "solid", "color": "red"}, "stroke": "black", "strokeWidth": [0.09525], "points": [{"x": 46, "y": 958, "directive": "moveTo"}, {"x": 136, "y": 958, "directive": "lineTo"}]}, {"type": "freeform", "fill": {"type": "solid", "color": "red"}, "stroke": "black", "strokeWidth": [0.09525], "points": [{"x": 1, "y": 140, "directive": "moveTo"}, {"x": 138, "y": 140, "directive": "lineTo"}]}, {"type": "freeform", "fill": {"type": "solid", "color": "red"}, "stroke": "black", "strokeWidth": [0.09525], "points": [{"x": 22, "y": 228, "directive": "moveTo"}, {"x": 139, "y": 228, "directive": "lineTo"}]}, {"type": "freeform", "fill": {"type": "solid", "color": "red"}, "stroke": "black", "strokeWidth": [0.09525], "points": [{"x": 22, "y": 162, "directive": "moveTo"}, {"x": 139, "y": 162, "directive": "lineTo"}]}, {"type": "freeform", "fill": {"type": "solid", "color": "red"}, "stroke": "black", "strokeWidth": [0.09525], "points": [{"x": 3, "y": 22, "directive": "moveTo"}, {"x": 140, "y": 22, "directive": "lineTo"}]}, {"type": "freeform", "fill": {"type": "solid", "color": "red"}, "stroke": "black", "strokeWidth": [0.09525], "points": [{"x": 140, "y": 958, "directive": "moveTo"}, {"x": 230, "y": 958, "directive": "lineTo"}]}, {"type": "freeform", "fill": {"type": "solid", "color": "#FFFF66"}, "stroke": "black", "strokeWidth": [0.09525], "points": [{"x": 258, "y": 228, "directive": "moveTo"}, {"x": 276, "y": 245, "directive": "lineTo"}, {"x": 277, "y": 692, "directive": "lineTo"}, {"x": 293, "y": 710, "directive": "lineTo"}, {"x": 293, "y": 809, "directive": "lineTo"}, {"x": 277, "y": 834, "directive": "lineTo"}, {"x": 276, "y": 924, "directive": "lineTo"}, {"x": 259, "y": 958, "directive": "lineTo"}, {"x": 232, "y": 959, "directive": "lineTo"}, {"x": 232, "y": 828, "directive": "lineTo"}, {"x": 263, "y": 828, "directive": "lineTo"}, {"x": 263, "y": 698, "directive": "lineTo"}, {"x": 232, "y": 698, "directive": "lineTo"}, {"x": 232, "y": 84, "directive": "lineTo"}, {"x": 250, "y": 84, "directive": "lineTo"}, {"x": 250, "y": 39, "directive": "lineTo"}, {"x": 232, "y": 39, "directive": "lineTo"}, {"x": 232, "y": 0, "directive": "lineTo"}, {"x": 258, "y": 0, "directive": "lineTo"}, {"x": 276, "y": 21, "directive": "lineTo"}, {"x": 276, "y": 139, "directive": "lineTo"}, {"x": 258, "y": 162, "directive": "lineTo"}, {"x": 258, "y": 228, "directive": "lineTo"}, {"directive": "close"}]}, {"type": "freeform", "fill": {"type": "solid", "color": "#FFFFFF"}, "stroke": "black", "strokeWidth": [0.09525], "points": [{"x": 251, "y": 277, "directive": "moveTo"}, {"x": 267, "y": 277, "directive": "lineTo"}, {"x": 267, "y": 404, "directive": "lineTo", "myPoint": 222}, {"x": 251, "y": 404, "directive": "lineTo", "myPoint": 222}, {"x": 251, "y": 277, "directive": "lineTo"}, {"directive": "close"}]}, {"type": "freeform", "fill": {"type": "solid", "color": "#FFFFFF"}, "stroke": "black", "strokeWidth": [0.09525], "points": [{"x": 240, "y": 500, "directive": "moveTo"}, {"x": 267, "y": 500, "directive": "lineTo"}, {"x": 267, "y": 668, "directive": "lineTo", "myPoint": 222}, {"x": 240, "y": 668, "directive": "lineTo", "myPoint": 222}, {"x": 240, "y": 500, "directive": "lineTo"}, {"directive": "close"}]}, {"type": "freeform", "fill": {"type": "solid", "color": "red"}, "stroke": "black", "strokeWidth": [0.09525], "points": [{"x": 251, "y": 405, "directive": "moveTo"}, {"x": 251, "y": 449, "directive": "lineTo"}, {"x": 266, "y": 449, "directive": "lineTo"}, {"x": 266, "y": 500, "directive": "lineTo"}]}, {"type": "freeform", "fill": {"type": "solid", "color": "red"}, "stroke": "black", "strokeWidth": [0.09525], "points": [{"x": 260, "y": 277, "directive": "moveTo"}, {"x": 260, "y": 256, "directive": "lineTo"}, {"x": 307, "y": 152, "directive": "lineTo"}, {"x": 307, "y": 9, "directive": "lineTo"}]}, {"type": "freeform", "fill": {"type": "solid", "color": "#FFFF66"}, "stroke": "black", "strokeWidth": [0.09525], "points": [{"x": 139, "y": 698, "directive": "moveTo"}, {"x": 255, "y": 698, "directive": "lineTo"}, {"x": 255, "y": 727, "directive": "lineTo", "myPoint": 222}, {"x": 139, "y": 727, "directive": "lineTo", "myPoint": 222}, {"x": 139, "y": 698, "directive": "lineTo"}, {"directive": "close"}]}, {"type": "freeform", "fill": "none", "stroke": "black", "points": [{"directive": "moveTo", "x": 0.003861111111111111, "y": 0.018583333333333334}, {"directive": "lineTo", "x": 0.006194444444444444, "y": 0.01938888888888889}]}, {"type": "freeform", "fill": "none", "stroke": "black", "points": [{"directive": "moveTo", "x": 0.003861111111111111, "y": 0.023}, {"directive": "lineTo", "x": 0.0064444444444444445, "y": 0.023}]}, {"type": "freeform", "fill": "none", "stroke": "black", "points": [{"directive": "moveTo", "x": 0.003861111111111111, "y": 0.0010833333333333333}, {"directive": "lineTo", "x": 0.0064444444444444445, "y": 0.0010833333333333333}]}, {"type": "freeform", "fill": "none", "stroke": "black", "points": [{"directive": "moveTo", "x": 0.003861111111111111, "y": 0.0023333333333333335}, {"directive": "lineTo", "x": 0.0064444444444444445, "y": 0.0023333333333333335}]}, {"type": "freeform", "fill": "none", "stroke": "black", "points": [{"directive": "moveTo", "x": 0.003861111111111111, "y": 2.777777777777778e-05}, {"directive": "lineTo", "x": 0.0064444444444444445, "y": 2.777777777777778e-05}]}], "height": 959, "width": 307}
